{
    "Prefix": "c",
    "No": "002",
    "Name": "承謙打電動",
    "Description": "承謙很喜歡打Apex，只是他的遊戲技巧不太好（量化來說，他的初始戰力值為a）\n因此他想透過不斷打b場Apex來增強他的Apex戰力值。\n他在遊戲中每擊殺一位玩家都可以增加c戰力值\n而他在每場遊戲的小隊排名也會影響戰力值：第一名+10、第二名+9、......、第十九名-8、第二十名-9\n每筆輸入有多行，第一行有三個整數a, b, c，其中-100≤a≤100、1≤b≤100、20≤c≤100，\n再來有b行，每行有兩個數字（以空格隔開），第一個數字代表他在該場遊戲擊殺人數（非負整數，小於10），第二個數字代表他在該場的小隊排名（1～20名）。\n輸出一個整數代表承謙最後的戰力值。",
    "Input": "0 2 4\n1 4\n0 1\n100 7 10\n0 20\n0 15\n3 11\n1 9\n0 17\n0 8\n4 2",
    "Output": "21\n175",
    "TEST": {
        "score": [100],
        "input": ["input/0", "input/1"],
        "output": ["output/0", "output/1"]
    }
}
